iterpop/__init__.py
iterpop/iterpop.py
iterpop-0.4.0.dist-info/AUTHORS.rst
iterpop-0.4.0.dist-info/LICENSE
iterpop-0.4.0.dist-info/METADATA
iterpop-0.4.0.dist-info/WHEEL
iterpop-0.4.0.dist-info/top_level.txt
iterpop-0.4.0.dist-info/RECORD
