Metadata-Version: 2.1
Name: iterpop
Version: 0.4.0
Summary: iterpop makes popping the value out of a singleton container safe and fun
Home-page: https://github.com/mmore500/iterpop
Author: Matthew Andres Moreno
Author-email: m.more500@gmail.com
License: MIT license
Keywords: iterpop
Platform: UNKNOWN
Classifier: Development Status :: 2 - Pre-Alpha
Classifier: Intended Audience :: Developers
Classifier: License :: OSI Approved :: MIT License
Classifier: Natural Language :: English
Classifier: Programming Language :: Python :: 3
Classifier: Programming Language :: Python :: 3.5
Classifier: Programming Language :: Python :: 3.6
Classifier: Programming Language :: Python :: 3.7
Classifier: Programming Language :: Python :: 3.8
Requires-Python: >=3.5
License-File: LICENSE
License-File: AUTHORS.rst
